.gitignore
.travis.yml
LICENSE
README.md
setup.cfg
setup.py
ci/requirements.txt
dnsadmin53/__init__.py
dnsadmin53/cli.py
dnsadmin53/core.py
dnsadmin53.egg-info/PKG-INFO
dnsadmin53.egg-info/SOURCES.txt
dnsadmin53.egg-info/dependency_links.txt
dnsadmin53.egg-info/requires.txt
dnsadmin53.egg-info/top_level.txt
tests/Route53_tests.py