Metadata-Version: 1.0
Name: dnsadmin53
Version: 0.0.1
Summary: DNS Admin tool for Route53 IAM/ARN Managment
Home-page: https://github.com/huit/python-dnsadmin53
Author: Harvard University Information Technology
Author-email: ithelp@harvard.edu
License: LICENSE
Platform: UNKNOWN
